[
    {
      "title": "Commonly used data types DO NOT include:",
      "choices": ["strings", "booleans", "alerts", "numbers"],
      "correct": 3
    },
    {
      "title": "The condition in an if / else statement is enclosed with ______.",
      "choices": ["quotes", "curly brackets", "parenthesis", "square brackets"],
      "correct": 3
    },
    {
      "title": "Arrays in JavaScript can be used to store ______.",
      "choices": ["numbers and strings", "other arrays", "booleans", "all of the above"],
      "correct": 4
    },
    {
      "title": "String values must be enclosed within ______ when being assigned to variables.",
      "choices": ["commas", "curly brackets", "quotes", "parenthesis"],
      "correct": 3
    },
    {
      "title": "A very useful tool used during development and debugging for printing content to the debugger is:",
      "choices": ["JavaScript", "terminal/bash", "for loops", "console.log"],
      "correct": 4
    },
    {
      "title": "Who invented JavaScript programming language?",
      "choices": ["Steve Jobs", "Brendan Eich", "Bill Gates", "James Gosling"],
      "correct": 2
    },
    {
      "title": "JavaScript and Java are the same?",
      "choices": [true, false],
      "correct": 2
    },
    {
      "title": "JavaScript CANNOT be used in which of these environments?",
      "choices": ["Web Browser", "Computer", "Coffee Maker", "Mobile Phone"],
      "correct": 3
    }
  ]